MANIFEST.in
README.rst
setup.py
./django_dbconn_retry/__init__.py
./django_dbconn_retry/tests/__init__.py
django_dbconn_retry/tests/__init__.py
django_dbconn_retry_coreteam.egg-info/PKG-INFO
django_dbconn_retry_coreteam.egg-info/SOURCES.txt
django_dbconn_retry_coreteam.egg-info/dependency_links.txt
django_dbconn_retry_coreteam.egg-info/top_level.txt
test_project/manage.py
test_project/test_project/__init__.py
test_project/test_project/settings.py
test_project/test_project/urls.py
test_project/test_project/wsgi.py